[{"id":1,"listing_id":"L_FINAL_TEST_999","type":"公寓","area":"BKK1","project":"侨联测试大厦","title":"测试房源 - 最终验证","price":"$800","layout":"1房1厅1卫","size":"50㎡","deposit":"押1付1","contract_term":"1年起","available_date":"即可入住","tags":"","highlights":"采光极好, 交通便利, 品牌家电, 拎包入住","cost_notes":"水 $0.5/吨，电 $0.25/度。","advisor_comment":"这套房子是我们在 BKK1 的样板房，视野非常开阔。","drawbacks":"临街可能会有一点点吵。","images":"[\"https://images.unsplash.com/photo-1522708323590-d24dbb6b0267?w=800\", \"https://images.unsplash.com/photo-1502672260266-1c1ef2d93688?w=800\"]","cover_image":"https://images.unsplash.com/photo-1522708323590-d24dbb6b0267?w=800","status":"draft","created_at":"2026-04-11 04:04:34","updated_at":"2026-04-11 04:04:34","floor":null,"source_text":null,"source_from":null,"notion_page_id":null,"property_type":null},
{"id":2,"listing_id":"L_FINAL_SUCCESS_001","type":"公寓","area":"BKK1","project":"侨联测试大厦","title":"测试房源 - 最终成功验证","price":"$800","layout":"1房1厅1卫","size":"50㎡","deposit":"押1付1","contract_term":"1年起","available_date":"即可入住","tags":"","highlights":"采光极好, 交通便利, 品牌家电, 拎包入住","cost_notes":"水 $0.5/吨，电 $0.25/度。","advisor_comment":"这套房子是我们在 BKK1 的样板房，视野非常开阔。","drawbacks":"临街可能会有一点点吵。","images":"[\"https://images.unsplash.com/photo-1522708323590-d24dbb6b0267?w=800\", \"https://images.unsplash.com/photo-1502672260266-1c1ef2d93688?w=800\"]","cover_image":"https://images.unsplash.com/photo-1522708323590-d24dbb6b0267?w=800","status":"published","created_at":"2026-04-11 04:04:57","updated_at":"2026-04-11 04:04:58","floor":null,"source_text":null,"source_from":null,"notion_page_id":null,"property_type":null}]
